effmap_demo/__init__.py
effmap_demo/effmap_demo.py
effmap_demo-0.0.2.dist-info/LICENSE.txt
effmap_demo-0.0.2.dist-info/METADATA
effmap_demo-0.0.2.dist-info/WHEEL
effmap_demo-0.0.2.dist-info/top_level.txt
effmap_demo-0.0.2.dist-info/RECORD
