Metadata-Version: 2.1
Name: effmap-demo
Version: 0.0.2
Summary: Streamlit demonstration of usage of regressor and HST object introduced in effmap
Home-page: https://github.com/ivanokhotnikov/effmap_demo/
Author: Ivan Okhotnikov
Author-email: ivan.okhotnikov@outlook.com
License: UNKNOWN
Platform: UNKNOWN
Classifier: Programming Language :: Python :: 3
Classifier: License :: OSI Approved :: MIT License
Classifier: Operating System :: OS Independent
Requires-Python: >=3.6
